warden_spex/__init__.py
warden_spex/models.py
warden_spex/pkg.py
warden_spex/spex.py
warden_spex/hashing/__init__.py
warden_spex/hashing/hash_array.py
warden_spex/hashing/hash_embedding.py
warden_spex/hashing/hash_int.py
warden_spex-0.0.95.dist-info/METADATA
warden_spex-0.0.95.dist-info/WHEEL
warden_spex-0.0.95.dist-info/licenses/LICENSE
warden_spex-0.0.95.dist-info/RECORD
