Metadata-Version: 2.4
Name: warden-spex
Version: 0.0.95
Summary: Statistical Proof of Execution (SPEX) by Warden Labs
Project-URL: Repository, https://github.com/warden-protocol/warden-spex
Author-email: Michele Dallachiesa <michele@wardenprotocol.org>
License-Expression: Apache-2.0
License-File: LICENSE
Classifier: Development Status :: 3 - Alpha
Classifier: Intended Audience :: Science/Research
Classifier: License :: OSI Approved
Requires-Python: >=3.12.8
Requires-Dist: pydantic>=2.10.6
Requires-Dist: rbloom>=1.5.2
Requires-Dist: scipy>=1.15.2
